{
  "id": "pricing-classic",
  "title": "Pricing – Classic",
  "description": "Classic pricing page with clean design",
  "license": {
    "spdx": "MIT",
    "redistribution": true
  },
  "uses": [
    {
      "category": "ui",
      "id": "pricing-card"
    }
  ],
  "dependencies": {
    "npm": [],
    "peer": ["react", "react-dom", "next"]
  },
  "patches": {
    "tailwindConfig": "tailwind.patch.json"
  },
  "imports": {
    "page": "./page.jsx",
    "mountPathHint": "app/pricing/page.tsx"
  },
  "version": "2025.01.01-1",
  "checksum": "sha256:REPLACE_ME"
}
